process_parser/__init__.py
process_parser/main.py
supercollider/__init__.py
supercollider/process_synths.scd
supercollider/windows_xp.wav
system_symphony-0.1.4.dist-info/LICENSE
system_symphony-0.1.4.dist-info/METADATA
system_symphony-0.1.4.dist-info/WHEEL
system_symphony-0.1.4.dist-info/entry_points.txt
system_symphony-0.1.4.dist-info/RECORD
