Metadata-Version: 2.1
Name: system-symphony
Version: 0.1.4
Summary: Explore the sonic world of your computer.
Home-page: https://github.com/dsmaugy/the-sounds-of-processes
Author: Darwin
Author-email: darwin78913@gmail.com
Requires-Python: >=3.8,<4.0
Classifier: Programming Language :: Python :: 3
Classifier: Programming Language :: Python :: 3.8
Classifier: Programming Language :: Python :: 3.9
Classifier: Programming Language :: Python :: 3.10
Classifier: Programming Language :: Python :: 3.11
Requires-Dist: click (>=8.1.3,<9.0.0)
Requires-Dist: psutil (>=5.9.4,<6.0.0)
Requires-Dist: python-osc (>=1.8.0,<2.0.0)
Project-URL: Repository, https://github.com/dsmaugy/the-sounds-of-processes
